tests/__init__.py
tests/conftest.py
tests/test_log_display.py
tests/test_mcts_player.py
tests/test_pixmap_differ.py
tests/test_play_controller.py
tests/test_playout.py
tests/test_plot_canvas.py
tests/test_rules_formatter.py
tests/test_scaled_label.py
tests/test_scaled_radio_button.py
tests/test_strength_adjuster.py
tests/test_strength_history_plot.py
tests/test_strength_plot.py
zero_play/__init__.py
zero_play/about_dialog.py
zero_play/diagram_writer.py
zero_play/game_display.py
zero_play/game_state.py
zero_play/grid_controls_ui.py
zero_play/grid_display.py
zero_play/heuristic.py
zero_play/live_qpainter.py
zero_play/log_display.py
zero_play/main_window.py
zero_play/mcts_player.py
zero_play/mcts_worker.py
zero_play/pixmap_differ.py
zero_play/play_controller.py
zero_play/player.py
zero_play/playout.py
zero_play/plot_canvas.py
zero_play/plot_canvas_dummy.py
zero_play/plot_perf.py
zero_play/plot_strengths.py
zero_play/process_display.py
zero_play/rules_formatter.py
zero_play/scaled_label.py
zero_play/scaled_radio_button.py
zero_play/strength_adjuster.py
zero_play/strength_history_plot.py
zero_play/strength_plot.py
zero_play/zero_perf.py
zero_play/zero_play.py
zero_play/zero_play_images_rc.py
zero_play/zero_play_rcc.py
zero_play/zero_play_rules_rc.py
zero_play/connect4/__init__.py
zero_play/connect4/display.py
zero_play/connect4/game.py
zero_play/connect4/neural_net.py
zero_play/models/__init__.py
zero_play/models/game.py
zero_play/models/match.py
zero_play/models/match_note.py
zero_play/models/match_player.py
zero_play/models/player.py
zero_play/othello/__init__.py
zero_play/othello/display.py
zero_play/othello/game.py
zero_play/tictactoe/__init__.py
zero_play/tictactoe/display.py
zero_play/tictactoe/state.py
zero_play-0.5.0.dist-info/LICENSE
zero_play-0.5.0.dist-info/METADATA
zero_play-0.5.0.dist-info/WHEEL
zero_play-0.5.0.dist-info/entry_points.txt
zero_play-0.5.0.dist-info/top_level.txt
zero_play-0.5.0.dist-info/RECORD
