Metadata-Version: 2.1
Name: zero-play
Version: 0.5.0
Summary: Teach a computer to play any game
Home-page: https://donkirkby.github.io/zero-play/
Author: Don Kirkby
Project-URL: Bug Reports, https://github.com/donkirkby/zero-play/issues
Project-URL: Source, https://github.com/donkirkby/zero-play
Keywords: boardgames alphazero machine learning mcts
Classifier: Development Status :: 3 - Alpha
Classifier: Intended Audience :: Developers
Classifier: Topic :: Games/Entertainment :: Board Games
Classifier: License :: OSI Approved :: MIT License
Classifier: Programming Language :: Python :: 3.8
License-File: LICENSE
Requires-Dist: numpy
Requires-Dist: matplotlib
Requires-Dist: PySide6
Requires-Dist: markdown
Requires-Dist: space-tracer
Requires-Dist: sqlalchemy
Requires-Dist: alembic
Provides-Extra: ml
Requires-Dist: tensorflow ; extra == 'ml'
Provides-Extra: ml-gpu
Requires-Dist: tensorflow-gpu ; extra == 'ml-gpu'
